pp3d/algorithm/types.py
pp3d/algorithm/genetic/genetic.py
pp3d/algorithm/genetic/types.py
pp3d/algorithm/hybrid/pso_ga_hybrid.py
pp3d/algorithm/hybrid/pso_types.py
pp3d/algorithm/pso/pso.py
pp3d/algorithm/pso/types.py
pp3d/common/algorithm_utils.py
pp3d/common/collision_detection.py
pp3d/common/decorators.py
pp3d/common/flight_angle_calculator.py
pp3d/common/interpolate.py
pp3d/common/streamlit_widgets.py
pp3d/common/types.py
pp3d/playground/code_template.py
pp3d/playground/genetic_algorithm_playground.py
pp3d/playground/i18n.py
pp3d/playground/playground.py
pp3d/playground/pso_algorithm_playground.py
pp3d/playground/pso_ga_hybrid_playground.py
pp3d/playground/types.py
pp3d/visualization/plotly_utils.py
pp3d-0.2.1.dist-info/METADATA
pp3d-0.2.1.dist-info/WHEEL
pp3d-0.2.1.dist-info/licenses/LICENSE
pp3d-0.2.1.dist-info/RECORD
