Metadata-Version: 2.4
Name: pp3d
Version: 0.2.1
Summary: A Python-based research and experimental framework for 3D path planning with terrain awareness, including algorithms, simulation, and interactive visualization.
Project-URL: Homepage, https://github.com/codeboyzhou/PathPlanner3D
Project-URL: Repository, https://github.com/codeboyzhou/PathPlanner3D.git
Project-URL: Issues, https://github.com/codeboyzhou/PathPlanner3D/issues
Project-URL: Documentation, https://github.com/codeboyzhou/PathPlanner3D/blob/main/README.md
Author-email: codeboyzhou <zhouchen9118@foxmail.com>
Maintainer-email: codeboyzhou <zhouchen9118@foxmail.com>
License:                                  Apache License
License-File: LICENSE
Keywords: 3d,GA,PSO,algorithm,path-planning,playground
Classifier: License :: OSI Approved :: Apache Software License
Classifier: Operating System :: OS Independent
Classifier: Programming Language :: Python :: 3.12
Requires-Python: >=3.12
Requires-Dist: loguru>=0.7.3
Requires-Dist: numpy>=2.3.4
Requires-Dist: pandas>=2.3.3
Requires-Dist: plotly>=6.3.1
Requires-Dist: pydantic>=2.12.3
Requires-Dist: scipy>=1.16.3
Requires-Dist: streamlit-ace>=0.1.1
Requires-Dist: streamlit>=1.51.0
